mlcube_gcp/__init__.py
mlcube_gcp/__main__.py
mlcube_gcp/gcp_run.py
mlcube_gcp/gcp_client/__init__.py
mlcube_gcp/gcp_client/client.py
mlcube_gcp/gcp_client/instance.py
mlcube_gcp/gcp_client/operation.py
mlcube_gcp/gcp_client/service.py
mlcube_gcp/tests/__init__.py
mlcube_gcp/tests/test_get_runner_class.py
mlcube_gcp/tests/test_data/platform_01.yaml
mlcube_gcp-0.0.9.dist-info/METADATA
mlcube_gcp-0.0.9.dist-info/WHEEL
mlcube_gcp-0.0.9.dist-info/entry_points.txt
mlcube_gcp-0.0.9.dist-info/top_level.txt
mlcube_gcp-0.0.9.dist-info/RECORD
