Metadata-Version: 2.1
Name: mlcube-gcp
Version: 0.0.9
License: Apache 2.0
Requires-Python: >=3.6
Requires-Dist: mlcube (==0.0.9)
Requires-Dist: google-api-python-client (==1.12.5)
Requires-Dist: ssh-config (==0.0.22)
Requires-Dist: omegaconf (==2.1.0)
